removeoverlap/__init__.py
removeoverlap/chan.py
removeoverlap/cut_bounding_box.py
removeoverlap/edge.py
removeoverlap/event.py
removeoverlap/event_pool.py
removeoverlap/event_type.py
removeoverlap/hrectangle.py
removeoverlap/overlap.py
removeoverlap/plot.py
removeoverlap/print.py
removeoverlap/remove_overlap.py
removeoverlap/split_boxes.py
removeoverlap-0.0.18.dist-info/METADATA
removeoverlap-0.0.18.dist-info/WHEEL
removeoverlap-0.0.18.dist-info/licenses/LICENSE
removeoverlap-0.0.18.dist-info/RECORD
